Metadata-Version: 1.1
Name: chippy
Version: 0.1.0
Summary: A pure Python module for creating various chiptune style waveforms
Home-page: https://github.com/benmoran56/chippy
Author: Benjamin Moran
Author-email: benmoran56@gmail.com
License: MIT
Keywords: audio synthesizer chiptune
Platform: UNKNOWN
Classifier: Topic :: Utilities
Classifier: Development Status :: 4 - Beta
Classifier: License :: OSI Approved :: MIT License
Classifier: Operating System :: OS Independent
Classifier: Programming Language :: Python
Classifier: Programming Language :: Python :: 3
